<?xml version="1.0" encoding="UTF-8" ?>
<OpenSearchDescription xmlns="http://a9.com/-/spec/opensearch/1.1/" xmlns:moz="http://www.mozilla.org/2006/browser/search/">
  <ShortName>Meta Stack Overflow</ShortName>
  <Description>Search Meta Stack Overflow: Q&amp;A about the site for professional and enthusiast programmers</Description>
  <InputEncoding>UTF-8</InputEncoding>
  <Image width="16" height="16" type="image/x-icon">https://meta.stackoverflow.com/Content/Sites/stackoverflowmeta/Img/favicon.ico?v=f4030900537d</Image>
  <Url type="text/html" method="get" template="https://meta.stackoverflow.com/search?q={searchTerms}"></Url>
</OpenSearchDescription>